CHANGES.rst
CONTRIBUTORS.rst
DEVELOP.rst
LICENSE.rst
MANIFEST.in
README.rst
setup.cfg
setup.py
docs/index.rst
src/collective/__init__.py
src/collective.iamisearch.egg-info/PKG-INFO
src/collective.iamisearch.egg-info/SOURCES.txt
src/collective.iamisearch.egg-info/dependency_links.txt
src/collective.iamisearch.egg-info/entry_points.txt
src/collective.iamisearch.egg-info/namespace_packages.txt
src/collective.iamisearch.egg-info/not-zip-safe
src/collective.iamisearch.egg-info/requires.txt
src/collective.iamisearch.egg-info/top_level.txt
src/collective/iamisearch/__init__.py
src/collective/iamisearch/configure.zcml
src/collective/iamisearch/interfaces.py
src/collective/iamisearch/permissions.zcml
src/collective/iamisearch/setuphandlers.py
src/collective/iamisearch/testing.py
src/collective/iamisearch/traversal.py
src/collective/iamisearch/upgrades.py
src/collective/iamisearch/upgrades.zcml
src/collective/iamisearch/browser/__init__.py
src/collective/iamisearch/browser/configure.zcml
src/collective/iamisearch/browser/controlpanel.py
src/collective/iamisearch/browser/utils.py
src/collective/iamisearch/browser/overrides/.gitkeep
src/collective/iamisearch/browser/static/.gitkeep
src/collective/iamisearch/browser/static/css/menu.css
src/collective/iamisearch/browser/static/js/menu.js
src/collective/iamisearch/faceted/__init__.py
src/collective/iamisearch/faceted/configure.zcml
src/collective/iamisearch/faceted/view.pt
src/collective/iamisearch/faceted/config/iam_folder_en.xml
src/collective/iamisearch/faceted/config/iam_folder_fr.xml
src/collective/iamisearch/faceted/config/iam_folder_nl.xml
src/collective/iamisearch/faceted/config/isearch_folder_en.xml
src/collective/iamisearch/faceted/config/isearch_folder_fr.xml
src/collective/iamisearch/faceted/config/isearch_folder_nl.xml
src/collective/iamisearch/faceted/widgets/__init__.py
src/collective/iamisearch/faceted/widgets/configure.zcml
src/collective/iamisearch/faceted/widgets/interfaces.py
src/collective/iamisearch/faceted/widgets/widget.pt
src/collective/iamisearch/faceted/widgets/widget.py
src/collective/iamisearch/locales/collective.iamisearch.pot
src/collective/iamisearch/locales/update.sh
src/collective/iamisearch/locales/fr/LC_MESSAGES/collective.iamisearch.po
src/collective/iamisearch/locales/nl/LC_MESSAGES/collective.iamisearch.po
src/collective/iamisearch/profiles/default/browserlayer.xml
