Metadata-Version: 2.1
Name: collective.iamisearch
Version: 1.1
Summary: Adds 'I am' and 'I search' dropdown menus in Plone
Home-page: https://pypi.python.org/pypi/collective.iamisearch
Author: Sebastien Sirtoli
Author-email: sebastien.sirtoli@affinitic.be
License: GPL version 2
Keywords: Python Plone
Platform: UNKNOWN
Classifier: Environment :: Web Environment
Classifier: Framework :: Plone
Classifier: Framework :: Plone :: 5.1
Classifier: Programming Language :: Python
Classifier: Programming Language :: Python :: 2.7
Classifier: Operating System :: OS Independent
Classifier: License :: OSI Approved :: GNU General Public License v2 (GPLv2)
Provides-Extra: test
